tdlm/__init__.py
tdlm/core.py
tdlm/plotting.py
tdlm/utils.py
tdlm_python-0.1.dist-info/LICENSE
tdlm_python-0.1.dist-info/METADATA
tdlm_python-0.1.dist-info/WHEEL
tdlm_python-0.1.dist-info/top_level.txt
tdlm_python-0.1.dist-info/RECORD
