Metadata-Version: 2.1
Name: tdlm-python
Version: 0.1
Summary: TDLM implementation for Python
Home-page: http://github.com/skjerns/TDLM-Python
Author: skjerns
Author-email: nomail@nomail.com
License: GPLv4
Classifier: Programming Language :: Python :: 3
Classifier: Operating System :: OS Independent
License-File: LICENSE
Requires-Dist: numpy
Requires-Dist: numba
